<?xml version="1.0" encoding="utf-8" ?>
<dwsync>
<file name="0033003_03.png" server="112.175.184.64//html/" local="131293553000000000" remote="131299348200000000" Dst="0" />
<file name="0033003_11.png" server="112.175.184.64//html/" local="131293553000000000" remote="131299348200000000" Dst="0" />
<file name="0033003_05.png" server="112.175.184.64//html/" local="131293553000000000" remote="131299348200000000" Dst="0" />
<file name="0033003_08.png" server="112.175.184.64//html/" local="131293553000000000" remote="131299348200000000" Dst="0" />
<file name="0033003_13.png" server="112.175.184.64//html/" local="131293553000000000" remote="131299348200000000" Dst="0" />
<file name="0033003_18.png" server="112.175.184.64//html/" local="131293553000000000" remote="131299348200000000" Dst="0" />
<file name="030303_03.png" server="112.175.184.64//html/" local="131292035620000000" remote="131299348200000000" Dst="0" />
<file name="11111111_03.png" server="112.175.184.64//html/" local="131287320900000000" remote="131299348200000000" Dst="0" />
<file name="111111_04.jpg" server="112.175.184.64//html/" local="131288592340000000" remote="131299348200000000" Dst="0" />
<file name="120212_03.png" server="112.175.184.64//html/" local="131291158020000000" remote="131299348200000000" Dst="0" />
<file name="1111111_02.png" server="112.175.184.64//html/" local="131291218500000000" remote="131299348200000000" Dst="0" />
<file name="120212_05.png" server="112.175.184.64//html/" local="131291158020000000" remote="131299348200000000" Dst="0" />
<file name="1231111111111_02.png" server="112.175.184.64//html/" local="131293576180000000" remote="131299348200000000" Dst="0" />
<file name="0111111111111_01.png" server="112.175.184.64//html/" local="131292833480000000" remote="131299348200000000" Dst="0" />
<file name="123456_03.png" server="112.175.184.64//html/" local="131291080520000000" remote="131299348200000000" Dst="0" />
<file name="123456_05.png" server="112.175.184.64//html/" local="131291080520000000" remote="131299348200000000" Dst="0" />
<file name="123456_07.png" server="112.175.184.64//html/" local="131291080520000000" remote="131299348200000000" Dst="0" />
<file name="123123123123_03.png" server="112.175.184.64//html/" local="131292037460000000" remote="131299348200000000" Dst="0" />
<file name="1243_03.png" server="112.175.184.64//html/" local="131290180560000000" remote="131299348200000000" Dst="0" />
<file name="342s.png" server="112.175.184.64//html/" local="131294710140000000" remote="131299348200000000" Dst="0" />
<file name="456.png" server="112.175.184.64//html/" local="131293639420000000" remote="131299348200000000" Dst="0" />
<file name="456_11.png" server="112.175.184.64//html/" local="131292787680000000" remote="131299348200000000" Dst="0" />
<file name="456_15.png" server="112.175.184.64//html/" local="131292787680000000" remote="131299348200000000" Dst="0" />
<file name="55555_19.png" server="112.175.184.64//html/" local="131292803320000000" remote="131299348200000000" Dst="0" />
<file name="999.png" server="112.175.184.64//html/" local="131293627020000000" remote="131299348200000000" Dst="0" />
<file name="alkj.png" server="112.175.184.64//html/" local="131296176740000000" remote="131299348200000000" Dst="0" />
<file name="123123.png" server="112.175.184.64//html/" local="131291995000000000" remote="131299348200000000" Dst="0" />
<file name="asd.png" server="112.175.184.64//html/" local="131293656500000000" remote="131299348200000000" Dst="0" />
<file name="asda_03.png" server="112.175.184.64//html/" local="131293676980000000" remote="131299348200000000" Dst="0" />
<file name="asda_06.png" server="112.175.184.64//html/" local="131293677000000000" remote="131299348200000000" Dst="0" />
<file name="best.png" server="112.175.184.64//html/" local="131284827140000000" remote="131299348200000000" Dst="0" />
<file name="allowto_landscape_2283.jpg" server="112.175.184.64//html/" local="131292891820000000" remote="131299348200000000" Dst="0" />
<file name="bestcamera1.png" server="112.175.184.64//html/" local="131284827140000000" remote="131299348200000000" Dst="0" />
<file name="bestcamera2.png" server="112.175.184.64//html/" local="131286839940000000" remote="131299348200000000" Dst="0" />
<file name="blog.png" server="112.175.184.64//html/" local="131284827180000000" remote="131299348200000000" Dst="0" />
<file name="btn_after.png" server="112.175.184.64//html/" local="131284827160000000" remote="131299348200000000" Dst="0" />
<file name="btn_before.png" server="112.175.184.64//html/" local="131284827160000000" remote="131299348200000000" Dst="0" />
<file name="bh.png" server="112.175.184.64//html/" local="131294130400000000" remote="131299348200000000" Dst="0" />
<file name="btn_stop.png" server="112.175.184.64//html/" local="131284827160000000" remote="131299348200000000" Dst="0" />
<file name="allowto_landscape_1298.jpg" server="112.175.184.64//html/" local="131239083000000000" remote="131299348200000000" Dst="0" />
<file name="casb_06.png" server="112.175.184.64//html/" local="131296126000000000" remote="131299348200000000" Dst="0" />
<file name="casb_08.png" server="112.175.184.64//html/" local="131296126000000000" remote="131299348200000000" Dst="0" />
<file name="cont.png" server="112.175.184.64//html/" local="131296103960000000" remote="131299348200000000" Dst="0" />
<file name="contentsbanner1.png" server="112.175.184.64//html/" local="131284827160000000" remote="131299348200000000" Dst="0" />
<file name="cvxb_03.png" server="112.175.184.64//html/" local="131296123640000000" remote="131299348200000000" Dst="0" />
<file name="D3400.png" server="112.175.184.64//html/" local="131291947440000000" remote="131299348200000000" Dst="0" />
<file name="D4s.png" server="112.175.184.64//html/" local="131291942640000000" remote="131299348200000000" Dst="0" />
<file name="D5.png" server="112.175.184.64//html/" local="131291937240000000" remote="131299348200000000" Dst="0" />
<file name="cscs.png" server="112.175.184.64//html/" local="131294089080000000" remote="131299348200000000" Dst="0" />
<file name="D500.png" server="112.175.184.64//html/" local="131291937240000000" remote="131299348200000000" Dst="0" />
<file name="D5300.png" server="112.175.184.64//html/" local="131291942660000000" remote="131299348200000000" Dst="0" />
<file name="D5500.png" server="112.175.184.64//html/" local="131291942660000000" remote="131299348200000000" Dst="0" />
<file name="D610.png" server="112.175.184.64//html/" local="131291942640000000" remote="131299348200000000" Dst="0" />
<file name="D5600.png" server="112.175.184.64//html/" local="131291937240000000" remote="131299348200000000" Dst="0" />
<file name="D7100.png" server="112.175.184.64//html/" local="131291942660000000" remote="131299348200000000" Dst="0" />
<file name="D7200.png" server="112.175.184.64//html/" local="131291942640000000" remote="131299348200000000" Dst="0" />
<file name="D810.png" server="112.175.184.64//html/" local="131291942640000000" remote="131299348200000000" Dst="0" />
<file name="Df.png" server="112.175.184.64//html/" local="131291942640000000" remote="131299348200000000" Dst="0" />
<file name="D810A.png" server="112.175.184.64//html/" local="131291942640000000" remote="131299348200000000" Dst="0" />
<file name="dsf_03.png" server="112.175.184.64//html/" local="131285922120000000" remote="131299348800000000" Dst="0" />
<file name="facebook.png" server="112.175.184.64//html/" local="131284827180000000" remote="131299348800000000" Dst="0" />
<file name="eventbanner1.png" server="112.175.184.64//html/" local="131285913060000000" remote="131299348800000000" Dst="0" />
<file name="eventbanner1_1.png" server="112.175.184.64//html/" local="131284214540000000" remote="131299348800000000" Dst="0" />
<file name="gy_111.png" server="112.175.184.64//html/" local="131284827160000000" remote="131299348800000000" Dst="0" />
<file name="gy_114.png" server="112.175.184.64//html/" local="131284827180000000" remote="131299348800000000" Dst="0" />
<file name="gy_115.png" server="112.175.184.64//html/" local="131284827180000000" remote="131299348800000000" Dst="0" />
<file name="gy_133.png" server="112.175.184.64//html/" local="131284827180000000" remote="131299348800000000" Dst="0" />
<file name="gy_146.png" server="112.175.184.64//html/" local="131284827200000000" remote="131299348800000000" Dst="0" />
<file name="gy_136.png" server="112.175.184.64//html/" local="131284827180000000" remote="131299348800000000" Dst="0" />
<file name="gy_143.png" server="112.175.184.64//html/" local="131284827180000000" remote="131299348800000000" Dst="0" />
<file name="home.png" server="112.175.184.64//html/" local="131291935640000000" remote="131299348800000000" Dst="0" />
<file name="gy_150.png" server="112.175.184.64//html/" local="131284827200000000" remote="131299348800000000" Dst="0" />
<file name="heart.png" server="112.175.184.64//html/" local="131292715780000000" remote="131299348800000000" Dst="0" />
<file name="icon1.png" server="112.175.184.64//html/" local="131284827080000000" remote="131299348800000000" Dst="0" />
<file name="icon1_1.png" server="112.175.184.64//html/" local="131284827080000000" remote="131299348800000000" Dst="0" />
<file name="icon2.png" server="112.175.184.64//html/" local="131284827080000000" remote="131299348800000000" Dst="0" />
<file name="icon3.png" server="112.175.184.64//html/" local="131284827080000000" remote="131299348800000000" Dst="0" />
<file name="icon3_3.png" server="112.175.184.64//html/" local="131284827100000000" remote="131299348800000000" Dst="0" />
<file name="icon2_2.png" server="112.175.184.64//html/" local="131284827100000000" remote="131299348800000000" Dst="0" />
<file name="icon4_4.png" server="112.175.184.64//html/" local="131284827100000000" remote="131299348800000000" Dst="0" />
<file name="icon4.png" server="112.175.184.64//html/" local="131284827080000000" remote="131299348800000000" Dst="0" />
<file name="icon5.png" server="112.175.184.64//html/" local="131284827080000000" remote="131299348800000000" Dst="0" />
<file name="info_btn.png" server="112.175.184.64//html/" local="131284827180000000" remote="131299348800000000" Dst="0" />
<file name="instar.png" server="112.175.184.64//html/" local="131284827180000000" remote="131299348800000000" Dst="0" />
<file name="icon5_5.png" server="112.175.184.64//html/" local="131284827100000000" remote="131299348800000000" Dst="0" />
<file name="jkl_02.png" server="112.175.184.64//html/" local="131290173700000000" remote="131299348800000000" Dst="0" />
<file name="login.png" server="112.175.184.64//html/" local="131284827080000000" remote="131299348800000000" Dst="0" />
<file name="logo.png" server="112.175.184.64//html/" local="131284827080000000" remote="131299348800000000" Dst="0" />
<file name="lens-1209823_1920.jpg" server="112.175.184.64//html/" local="131292921640000000" remote="131299348800000000" Dst="0" />
<file name="jkhm.png" server="112.175.184.64//html/" local="131294503520000000" remote="131299348800000000" Dst="0" />
<file name="maincamera.png" server="112.175.184.64//html/" local="131284827100000000" remote="131299348800000000" Dst="0" />
<file name="main.png" server="112.175.184.64//html/" local="131284214520000000" remote="131299348800000000" Dst="0" />
<file name="more.png" server="112.175.184.64//html/" local="131284827120000000" remote="131299348800000000" Dst="0" />
<file name="more_btn.png" server="112.175.184.64//html/" local="131284827160000000" remote="131299348800000000" Dst="0" />
<file name="new.png" server="112.175.184.64//html/" local="131284827120000000" remote="131299348800000000" Dst="0" />
<file name="nhmj_16.png" server="112.175.184.64//html/" local="131296183040000000" remote="131299348800000000" Dst="0" />
<file name="nhmj_18.png" server="112.175.184.64//html/" local="131296183060000000" remote="131299348800000000" Dst="0" />
<file name="newcamera.png" server="112.175.184.64//html/" local="131284827140000000" remote="131299348800000000" Dst="0" />
<file name="nhmj_20.png" server="112.175.184.64//html/" local="131296183060000000" remote="131299348800000000" Dst="0" />
<file name="nhmj_22.png" server="112.175.184.64//html/" local="131296183060000000" remote="131299348800000000" Dst="0" />
<file name="polaroid.png" server="112.175.184.64//html/" local="131291950780000000" remote="131299348800000000" Dst="0" />
<file name="photographer-819365_960_720.jpg" server="112.175.184.64//html/" local="131241257540000000" remote="131299348800000000" Dst="0" />
<file name="qaxs.png" server="112.175.184.64//html/" local="131296106160000000" remote="131299348800000000" Dst="0" />
<file name="qweqwe_06.png" server="112.175.184.64//html/" local="131292943340000000" remote="131299348800000000" Dst="0" />
<file name="qweqwe_08.png" server="112.175.184.64//html/" local="131292943340000000" remote="131299348800000000" Dst="0" />
<file name="qqwe.png" server="112.175.184.64//html/" local="131294505420000000" remote="131299348800000000" Dst="0" />
<file name="qweqwe_10.png" server="112.175.184.64//html/" local="131292943340000000" remote="131299348800000000" Dst="0" />
<file name="qweqwe_12.png" server="112.175.184.64//html/" local="131292943340000000" remote="131299348800000000" Dst="0" />
<file name="nikon-614640_1920.jpg" server="112.175.184.64//html/" local="131292916260000000" remote="131299348800000000" Dst="0" />
<file name="qwezxc_03.png" server="112.175.184.64//html/" local="131293698000000000" remote="131299348800000000" Dst="0" />
<file name="qwezxc_05.png" server="112.175.184.64//html/" local="131293698000000000" remote="131299348800000000" Dst="0" />
<file name="sdf.png" server="112.175.184.64//html/" local="131293637280000000" remote="131299348800000000" Dst="0" />
<file name="qwqw_02.png" server="112.175.184.64//html/" local="131290167900000000" remote="131299348800000000" Dst="0" />
<file name="sdfsdf_06.png" server="112.175.184.64//html/" local="131292040520000000" remote="131299348800000000" Dst="0" />
<file name="sdfsx.png" server="112.175.184.64//html/" local="131293654160000000" remote="131299348800000000" Dst="0" />
<file name="sd_03.png" server="112.175.184.64//html/" local="131292201000000000" remote="131299348800000000" Dst="0" />
<file name="sub01_new.png" server="112.175.184.64//html/" local="131291935640000000" remote="131299348800000000" Dst="0" />
<file name="tgfc.png" server="112.175.184.64//html/" local="131294115080000000" remote="131299348800000000" Dst="0" />
<file name="tree-838667_1280.jpg" server="112.175.184.64//html/" local="131292903060000000" remote="131299348800000000" Dst="0" />
<file name="sub01_main.png" server="112.175.184.64//html/" local="131291934000000000" remote="131299348800000000" Dst="0" />
<file name="sub01_maincamera.png" server="112.175.184.64//html/" local="131291951740000000" remote="131299348800000000" Dst="0" />
<file name="utube.png" server="112.175.184.64//html/" local="131284827180000000" remote="131299348800000000" Dst="0" />
<file name="we_94.png" server="112.175.184.64//html/" local="131290123460000000" remote="131299348800000000" Dst="0" />
<file name="wer.png" server="112.175.184.64//html/" local="131294445040000000" remote="131299348800000000" Dst="0" />
<file name="xcvs.png" server="112.175.184.64//html/" local="131294082720000000" remote="131299348800000000" Dst="0" />
<file name="xcvsd.png" server="112.175.184.64//html/" local="131294391060000000" remote="131299348800000000" Dst="0" />
<file name="zxc_02.png" server="112.175.184.64//html/" local="131290169660000000" remote="131299348800000000" Dst="0" />
<file name="Untitled-1_02.png" server="112.175.184.64//html/" local="131285907940000000" remote="131299348800000000" Dst="0" />
<file name="bcvfdf.png" server="112.175.184.64//html/" local="131298043200000000" remote="131299348200000000" Dst="0" />
<file name="cvsde.png" server="112.175.184.64//html/" local="131298052100000000" remote="131299348200000000" Dst="0" />
<file name="mjgh.png" server="112.175.184.64//html/" local="131298692500000000" remote="131299348800000000" Dst="0" />
<file name="fgj.jpg" server="112.175.184.64//html/" local="131298038380000000" remote="131299348800000000" Dst="0" />
<file name="uio.png" server="112.175.184.64//html/" local="131298706900000000" remote="131299348800000000" Dst="0" />
<file name="tuiol_03.png" server="112.175.184.64//html/" local="131298851680000000" remote="131299348800000000" Dst="0" />
<file name="vxc.png" server="112.175.184.64//html/" local="131298044480000000" remote="131299348800000000" Dst="0" />
<file name="wnb.png" server="112.175.184.64//html/" local="131298039740000000" remote="131299348800000000" Dst="0" />
<file name="zbs.png" server="112.175.184.64//html/" local="131298046100000000" remote="131299348800000000" Dst="0" />
<file name="awe_02.png" server="112.175.184.64//html/" local="131299923740000000" remote="131302806000000000" Dst="0" />
<file name="cse_02.png" server="112.175.184.64//html/" local="131299918420000000" remote="131302806000000000" Dst="0" />
<file name="blop_03.png" server="112.175.184.64//html/" local="131299888300000000" remote="131302806000000000" Dst="0" />
<file name="blop_05.png" server="112.175.184.64//html/" local="131299888300000000" remote="131302806000000000" Dst="0" />
<file name="uij_02.png" server="112.175.184.64//html/" local="131299928060000000" remote="131302806000000000" Dst="0" />
</dwsync>